jetty/__init__.py
jetty/__version__.py
jetty/cli/__init__.py
jetty/cli/application.py
jetty/project.py
jetty/schemas/poetry-schema.json
jetty/util/__init__.py
jetty/util/dicttools.py
jetty-0.2.3.dist-info/entry_points.txt
jetty-0.2.3.dist-info/WHEEL
jetty-0.2.3.dist-info/METADATA
jetty-0.2.3.dist-info/RECORD
