Metadata-Version: 2.1
Name: jetty
Version: 0.2.3
Summary: 
License: MPL-2.0
Author: Andrew Halberstadt
Author-email: ahal@pm.me
Requires-Python: >=2.7, !=3.0.*, !=3.1.*, !=3.2.*, !=3.3.*
Classifier: License :: OSI Approved
Classifier: Programming Language :: Python :: 2
Classifier: Programming Language :: Python :: 2.7
Classifier: Programming Language :: Python :: 3
Classifier: Programming Language :: Python :: 3.4
Classifier: Programming Language :: Python :: 3.5
Classifier: Programming Language :: Python :: 3.6
Classifier: Programming Language :: Python :: 3.7
Requires-Dist: cleo (>=0.6.7,<0.7.0)
Requires-Dist: poetry (>=0.12.11,<0.13.0)
Requires-Dist: tomlkit (>=0.5.3,<0.6.0)
